notion/__init__.py
notion/get_provider_info.py
notion/hooks/__init__.py
notion/hooks/notion.py
notion/operators/__init__.py
notion/operators/notion.py
notion/sensors/__init__.py
airflow_provider_notion-0.0.1.1.dist-info/METADATA
airflow_provider_notion-0.0.1.1.dist-info/WHEEL
airflow_provider_notion-0.0.1.1.dist-info/entry_points.txt
airflow_provider_notion-0.0.1.1.dist-info/licenses/LICENSE
airflow_provider_notion-0.0.1.1.dist-info/RECORD
