Metadata-Version: 2.4
Name: airflow-provider-notion
Version: 0.0.1.1
Summary: Airflow provider for Notion API integration
Project-URL: Homepage, https://github.com/yourusername/airflow-provider-notion
Project-URL: Repository, https://github.com/yourusername/airflow-provider-notion
Project-URL: Documentation, https://github.com/yourusername/airflow-provider-notion
Author-email: Your Name <your.email@example.com>
License-Expression: Apache-2.0
License-File: LICENSE
Keywords: airflow,api,notion,provider
Classifier: Development Status :: 3 - Alpha
Classifier: Intended Audience :: Developers
Classifier: License :: OSI Approved :: Apache Software License
Classifier: Programming Language :: Python :: 3
Classifier: Programming Language :: Python :: 3.8
Classifier: Programming Language :: Python :: 3.9
Classifier: Programming Language :: Python :: 3.10
Classifier: Programming Language :: Python :: 3.11
Classifier: Topic :: Software Development :: Libraries :: Python Modules
Classifier: Topic :: System :: Monitoring
Requires-Python: >=3.8
Requires-Dist: apache-airflow>=2.3.0
Requires-Dist: requests>=2.25.0
Provides-Extra: dev
Requires-Dist: black>=21.0; extra == 'dev'
Requires-Dist: flake8>=3.8; extra == 'dev'
Requires-Dist: mypy>=0.900; extra == 'dev'
Requires-Dist: pytest-cov>=2.0; extra == 'dev'
Requires-Dist: pytest>=6.0; extra == 'dev'
